Makefile
README.rst
files/#wtfpl.txt#
files/apache.txt
files/artistic.txt
files/eclipse.txt
files/gpl.txt
files/isc.txt
files/lgpl.txt
files/mit.txt
files/mozilla.txt
files/unlicense.txt
files/wtfpl.txt
li/__init__.py
li/cache.py
li/cli.py
li/errors.py
li/license.py
li-0.1.3.dist-info/DESCRIPTION.rst
li-0.1.3.dist-info/METADATA
li-0.1.3.dist-info/RECORD
li-0.1.3.dist-info/WHEEL
li-0.1.3.dist-info/entry_points.txt
li-0.1.3.dist-info/metadata.json
li-0.1.3.dist-info/pbr.json
li-0.1.3.dist-info/top_level.txt
scripts/__init__.py
scripts/bump.py
